{
  "db_name": "PostgreSQL",
  "query": "UPDATE \"session\" SET last_seen_at = now() WHERE id = $1 RETURNING id, user_id, platform AS \"platform: SessionPlatform\", browser AS \"browser: SessionBrowser\", created_at, last_seen_at",
  "describe": {
    "columns": [
      {
        "ordinal": 0,
        "name": "id",
        "type_info": "Uuid"
      },
      {
        "ordinal": 1,
        "name": "user_id",
        "type_info": "Uuid"
      },
      {
        "ordinal": 2,
        "name": "platform: SessionPlatform",
        "type_info": {
          "Custom": {
            "name": "session_platform",
            "kind": {
              "Enum": [
                "macos",
                "windows",
                "linux",
                "ios",
                "android",
                "unknown"
              ]
            }
          }
        }
      },
      {
        "ordinal": 3,
        "name": "browser: SessionBrowser",
        "type_info": {
          "Custom": {
            "name": "session_browser",
            "kind": {
              "Enum": [
                "chrome",
                "firefox",
                "safari",
                "edge",
                "opera",
                "unknown"
              ]
            }
          }
        }
      },
      {
        "ordinal": 4,
        "name": "created_at",
        "type_info": "Timestamptz"
      },
      {
        "ordinal": 5,
        "name": "last_seen_at",
        "type_info": "Timestamptz"
      }
    ],
    "parameters": {
      "Left": [
        "Uuid"
      ]
    },
    "nullable": [
      false,
      false,
      false,
      false,
      false,
      false
    ]
  },
  "hash": "d6b284ac6ffd54d7ffea4a96957a1d8fd732c063e81376d06abd24dd72744b09"
}
